{"otherData": {},"traceEvents":[{"cat":"function","dur":561485,"name":"Window creating","ph":"X","pid":0,"tid":3971530079,"ts":227678467010},{"cat":"function","dur":256,"name":"Shunya::WindowMaker::SetVSync","ph":"X","pid":0,"tid":3971530079,"ts":227679033524},{"cat":"function","dur":685716,"name":"Shunya::WindowMaker::Init","ph":"X","pid":0,"tid":3971530079,"ts":227678348254},{"cat":"function","dur":685736,"name":"Shunya::WindowMaker::WindowMaker","ph":"X","pid":0,"tid":3971530079,"ts":227678348253},{"cat":"function","dur":167,"name":"Shunya::WindowMaker::SetVSync","ph":"X","pid":0,"tid":3971530079,"ts":227679034046},{"cat":"function","dur":16,"name":"Shunya::OpenGLRendererAPI::Init","ph":"X","pid":0,"tid":3971530079,"ts":227679034268},{"cat":"function","dur":32,"name":"Shunya::RendererCommand::Init","ph":"X","pid":0,"tid":3971530079,"ts":227679034267},{"cat":"function","dur":44,"name":"Shunya::OpenGLVertexArray::OpenGLVertexArray","ph":"X","pid":0,"tid":3971530079,"ts":227679034332},{"cat":"function","dur":46,"name":"Shunya::OpenglVertexBuffer::OpenglVertexBuffer","ph":"X","pid":0,"tid":3971530079,"ts":227679034425},{"cat":"function","dur":0,"name":"Shunya::OpenglVertexBuffer::Bind","ph":"X","pid":0,"tid":3971530079,"ts":227679034546},{"cat":"function","dur":41,"name":"Shunya::OpenGLVertexArray::AddVertexBuffer","ph":"X","pid":0,"tid":3971530079,"ts":227679034545},{"cat":"function","dur":125,"name":"Shunya::OpenglIndexBuffer::OpenglIndexBuffer","ph":"X","pid":0,"tid":3971530079,"ts":227679034997},{"cat":"function","dur":1,"name":"Shunya::OpenglIndexBuffer::Bind","ph":"X","pid":0,"tid":3971530079,"ts":227679035155},{"cat":"function","dur":17,"name":"Shunya::OpenGLVertexArray::SetIndexBuffer","ph":"X","pid":0,"tid":3971530079,"ts":227679035155},{"cat":"function","dur":37,"name":"Shunya::OpenGLTexture2D::OpenGLTexture2D","ph":"X","pid":0,"tid":3971530079,"ts":227679035208},{"cat":"function","dur":13,"name":"Shunya::OpenGLTexture2D::SetData","ph":"X","pid":0,"tid":3971530079,"ts":227679035273},{"cat":"function","dur":371,"name":"Shunya::OpenGLShader::ReadFile","ph":"X","pid":0,"tid":3971530079,"ts":227679035646},{"cat":"function","dur":1083,"name":"Shunya::OpenGLShader::PreProcess","ph":"X","pid":0,"tid":3971530079,"ts":227679036063},{"cat":"function","dur":11206,"name":"Shunya::OpenGLShader::CompileOrGetVulkanBinaries","ph":"X","pid":0,"tid":3971530079,"ts":227679037190},{"cat":"function","dur":1368,"name":"Shunya::OpenGLShader::CompileOrGetOpenGLBinaries","ph":"X","pid":0,"tid":3971530079,"ts":227679048550},{"cat":"function","dur":1005,"name":"Shunya::OpenGLShader::CreateProgram","ph":"X","pid":0,"tid":3971530079,"ts":227679049964},{"cat":"function","dur":16199,"name":"Shunya::OpenGLShader::OpenGLShader","ph":"X","pid":0,"tid":3971530079,"ts":227679035372},{"cat":"function","dur":9,"name":"Shunya::OpenGLShader::Bind","ph":"X","pid":0,"tid":3971530079,"ts":227679051629},{"cat":"function","dur":9,"name":"Shunya::OpenGLShader::SetIntArray","ph":"X","pid":0,"tid":3971530079,"ts":227679051656},{"cat":"function","dur":17711,"name":"Shunya::Renderer2D::Init","ph":"X","pid":0,"tid":3971530079,"ts":227679034313},{"cat":"function","dur":17812,"name":"Shunya::Renderer::Init","ph":"X","pid":0,"tid":3971530079,"ts":227679034265},{"cat":"function","dur":624,"name":"Shunya::Application::PushOverlay","ph":"X","pid":0,"tid":3971530079,"ts":227679052098},{"cat":"function","dur":704525,"name":"Shunya::Application::Application","ph":"X","pid":0,"tid":3971530079,"ts":227678348247},{"cat":"function","dur":18348,"name":"Shunya::OpenGLTexture2D::OpenGLTexture2D","ph":"X","pid":0,"tid":3971530079,"ts":227679052808},{"cat":"function","dur":19270,"name":"Shunya::OpenGLTexture2D::OpenGLTexture2D","ph":"X","pid":0,"tid":3971530079,"ts":227679071258},{"cat":"function","dur":43250,"name":"Shunya::OpenGLTexture2D::OpenGLTexture2D","ph":"X","pid":0,"tid":3971530079,"ts":227679090689},{"cat":"function","dur":43952,"name":"Shunya::Application::PushLayer","ph":"X","pid":0,"tid":3971530079,"ts":227679090657}]}